odoo/addons/base_location_geonames_import/README.rst
odoo/addons/base_location_geonames_import/__init__.py
odoo/addons/base_location_geonames_import/__manifest__.py
odoo/addons/base_location_geonames_import/data/res_country_data.xml
odoo/addons/base_location_geonames_import/i18n/am.po
odoo/addons/base_location_geonames_import/i18n/ar.po
odoo/addons/base_location_geonames_import/i18n/base_location_geonames_import.pot
odoo/addons/base_location_geonames_import/i18n/bg.po
odoo/addons/base_location_geonames_import/i18n/bs.po
odoo/addons/base_location_geonames_import/i18n/ca.po
odoo/addons/base_location_geonames_import/i18n/cs.po
odoo/addons/base_location_geonames_import/i18n/da.po
odoo/addons/base_location_geonames_import/i18n/de.po
odoo/addons/base_location_geonames_import/i18n/el_GR.po
odoo/addons/base_location_geonames_import/i18n/en_GB.po
odoo/addons/base_location_geonames_import/i18n/es.po
odoo/addons/base_location_geonames_import/i18n/es_AR.po
odoo/addons/base_location_geonames_import/i18n/es_CL.po
odoo/addons/base_location_geonames_import/i18n/es_CO.po
odoo/addons/base_location_geonames_import/i18n/es_CR.po
odoo/addons/base_location_geonames_import/i18n/es_DO.po
odoo/addons/base_location_geonames_import/i18n/es_EC.po
odoo/addons/base_location_geonames_import/i18n/es_ES.po
odoo/addons/base_location_geonames_import/i18n/es_MX.po
odoo/addons/base_location_geonames_import/i18n/es_PE.po
odoo/addons/base_location_geonames_import/i18n/es_PY.po
odoo/addons/base_location_geonames_import/i18n/es_VE.po
odoo/addons/base_location_geonames_import/i18n/et.po
odoo/addons/base_location_geonames_import/i18n/eu.po
odoo/addons/base_location_geonames_import/i18n/fa.po
odoo/addons/base_location_geonames_import/i18n/fi.po
odoo/addons/base_location_geonames_import/i18n/fr.po
odoo/addons/base_location_geonames_import/i18n/fr_CA.po
odoo/addons/base_location_geonames_import/i18n/fr_CH.po
odoo/addons/base_location_geonames_import/i18n/gl.po
odoo13_addon_base_location_geonames_import-13.0.2.0.1.dist-info/METADATA
odoo13_addon_base_location_geonames_import-13.0.2.0.1.dist-info/WHEEL
odoo13_addon_base_location_geonames_import-13.0.2.0.1.dist-info/top_level.txt
odoo13_addon_base_location_geonames_import-13.0.2.0.1.dist-info/RECORD
